olxapi.py
olxApi-0.2.1.dist-info/METADATA
olxApi-0.2.1.dist-info/WHEEL
olxApi-0.2.1.dist-info/top_level.txt
olxApi-0.2.1.dist-info/RECORD
