Metadata-Version: 2.1
Name: olxApi
Version: 0.2.1
Summary: A simple OLX scraper module
Home-page: https://github.com/kcoelho79/OLXApi
Author: Kleber Coelho
Author-email: kleber.amg79@gmail.com
Requires-Python: >=3.6
Requires-Dist: beautifulsoup4
Requires-Dist: requests
